{
   "teachers":
   [
      {
         "classId":
         [
            17,
            18
         ],
         "teacherId":300000000000018,
         "courseCode":1,
         "name":"测试老师一",
         "idNo":"2001",
         "subjectId":1
      },
      {
         "classId":
         [
            18,
            17
         ],
         "teacherId":300000000000020,
         "courseCode":3,
         "name":"一年二班老师",
         "idNo":"1234",
         "subjectId":3
      }

   ],
   "students":
   [
      {
         "classId":18,
         "goalId":
         [
            236,
            237
         ],
         "name":"刘梅梅",
         "idNo":"1678",
         "orgId":2
      },
      {
         "classId":17,
         "goalId":
         [
            246,
            245,
            243,
            242,
            236,
            237,
            234,
            239,
            240
         ],
         "name":"李小伟",
         "idNo":"1024",
         "orgId":2
      },
      {
         "classId":17,
         "goalId":
         [
            225,
            245,
            243,
            242,
            236,
            237,
            234,
            239,
            240,
            246
         ],
         "name":"测试学生",
         "idNo":"1001",
         "orgId":2
      },
      {
         "classId":18,
         "goalId":
         [
            243
         ],
         "name":"王小军",
         "idNo":"1022",
         "orgId":2
      }

   ],
   "courses":
   [
      {
         "period":2,
         "lessonNo":121,
         "goalId":242,
         "unitName":"数学第二单元",
         "sortNumber":1.0,
         "name":"生活数学",
         "unitId":43,
         "typeId":1,
         "subjectId":2
      },
      {
         "period":2,
         "lessonNo":122,
         "goalId":243,
         "unitName":"数学第二单元",
         "sortNumber":2.0,
         "name":"生活数学",
         "unitId":43,
         "typeId":1,
         "subjectId":2
      },
      {
         "period":4,
         "lessonNo":123,
         "goalId":245,
         "unitName":"数学第二单元",
         "sortNumber":3.0,
         "name":"生活数学",
         "unitId":43,
         "typeId":1,
         "subjectId":2
      },
      {
         "period":4,
         "lessonNo":124,
         "goalId":246,
         "unitName":"数学第二单元",
         "sortNumber":4.0,
         "name":"生活数学",
         "unitId":43,
         "typeId":1,
         "subjectId":2
      },
      {
         "period":2,
         "lessonNo":118,
         "goalId":234,
         "unitName":"语文第二单元",
         "sortNumber":5.0,
         "name":"生活语文",
         "unitId":42,
         "typeId":1,
         "subjectId":1
      },
      {
         "period":4,
         "lessonNo":119,
         "goalId":236,
         "unitName":"语文第二单元",
         "sortNumber":6.0,
         "name":"生活语文",
         "unitId":42,
         "typeId":1,
         "subjectId":1
      },
      {
         "period":4,
         "lessonNo":120,
         "goalId":237,
         "unitName":"语文第二单元",
         "sortNumber":7.0,
         "name":"生活语文",
         "unitId":42,
         "typeId":1,
         "subjectId":1
      },
      {
         "period":2,
         "lessonNo":115,
         "goalId":225,
         "unitName":"语文第一单元",
         "sortNumber":8.0,
         "name":"生活语文",
         "unitId":40,
         "typeId":1,
         "subjectId":1
      },
      {
         "period":4,
         "lessonNo":116,
         "goalId":239,
         "unitName":"数学第一单元",
         "sortNumber":9.0,
         "name":"生活语文",
         "unitId":41,
         "typeId":1,
         "subjectId":1
      },
      {
         "period":4,
         "lessonNo":117,
         "goalId":240,
         "unitName":"数学第一单元",
         "sortNumber":10.0,
         "name":"生活语文",
         "unitId":41,
         "typeId":1,
         "subjectId":1
      }

   ],
   "subjects":
   [
      {
         "subjectNumber":50,
         "subjectId":1,
         "subjectName":"生活语文"
      },
      {
         "subjectNumber":50,
         "subjectId":2,
         "subjectName":"生活数学"
      },
      {
         "subjectNumber":50,
         "subjectId":3,
         "subjectName":"生活适应"
      },
      {
         "subjectNumber":30,
         "subjectId":4,
         "subjectName":"劳动技能"
      },
      {
         "subjectNumber":40,
         "subjectId":5,
         "subjectName":"唱游与律动"
      },
      {
         "subjectNumber":50,
         "subjectId":6,
         "subjectName":"绘画与手工"
      },
      {
         "subjectNumber":40,
         "subjectId":7,
         "subjectName":"运动与保健"
      },
      {
         "subjectNumber":30,
         "subjectId":8,
         "subjectName":"信息技术"
      },
      {
         "subjectNumber":20,
         "subjectId":9,
         "subjectName":"康复训练"
      }

   ],
   "classrooms":
   [
      {
         "classroomNo":"100",
         "classroomCode":2,
         "classroomName":"阳光教室",
         "maxStudents":49,
         "minStudents":10,
         "typeId":1
      },
      {
         "classroomNo":"100",
         "classroomCode":17,
         "classroomName":"强国班",
         "maxStudents":50,
         "minStudents":2,
         "typeId":1
      }

   ],
   "tools":
   [
      {
         "code":6,
         "name":"数字卡片",
         "count":1,
         "typeId":1
      },
      {
         "code":7,
         "name":"动物卡片",
         "count":1,
         "typeId":1
      },
      {
         "code":8,
         "name":"字母卡片",
         "count":1,
         "typeId":1
      },
      {
         "code":9,
         "name":"积木",
         "count":1,
         "typeId":3
      },
      {
         "code":10,
         "name":"看图识字",
         "count":1,
         "typeId":5
      },
      {
         "code":11,
         "name":"人体器官",
         "count":1,
         "typeId":9
      },
      {
         "code":12,
         "name":"动物标本",
         "count":1,
         "typeId":10
      },
      {
         "code":13,
         "name":"地球仪",
         "count":1,
         "typeId":1
      },
      {
         "code":25,
         "name":"派出所",
         "count":1,
         "typeId":13
      },
      {
         "code":26,
         "name":"居委会",
         "count":1,
         "typeId":13
      },
      {
         "code":27,
         "name":"微笑",
         "count":1,
         "typeId":13
      },
      {
         "code":29,
         "name":"沙发",
         "count":1,
         "typeId":11
      },
      {
         "code":30,
         "name":"床",
         "count":0,
         "typeId":11
      },
      {
         "code":31,
         "name":"电视",
         "count":1,
         "typeId":11
      },
      {
         "code":33,
         "name":"出租车",
         "count":1,
         "typeId":11
      },
      {
         "code":34,
         "name":"飞机",
         "count":1,
         "typeId":11
      },
      {
         "code":35,
         "name":"公交车",
         "count":1,
         "typeId":11
      },
      {
         "code":36,
         "name":"火车",
         "count":1,
         "typeId":11
      }

   ],
   "schedule":
   {
      "startTermBegin":"2021-09-30",
      "startTermEnd":"2021-10-15",
      "lessonNumAm":4,
      "lessonNumPm":4,
      "timeLength":40,
      "monday":1,
      "tuesday":1,
      "wednesday":2,
      "thursday":1,
      "friday":1,
      "saturday":0,
      "sunday":0,
      "semester":"2020-2022-1",
      "orgId":2,
      "holiday":
      [
         "2022-01-01",
         "2022-01-02",
         "2021-06-12",
         "2021-06-13",
         "2021-06-14",
         "2021-09-19",
         "2021-09-20",
         "2021-09-21",
         "2021-10-01",
         "2021-10-02",
         "2021-10-03",
         "2021-10-04",
         "2021-10-05",
         "2021-10-06",
         "2021-10-07",
         "2021-12-31"
      ]

   }

}